cfgtemplater/__init__.py
cfgtemplater/base_template.py
cfgtemplater/command_line.py
cfgtemplater/config_template.py
cfgtemplater/extensions/__init__.py
cfgtemplater/extensions/ip_filters.py
cfgtemplater/extensions/ip_tests.py
cfgtemplater-0.0.2.dist-info/LICENSE.txt
cfgtemplater-0.0.2.dist-info/METADATA
cfgtemplater-0.0.2.dist-info/WHEEL
cfgtemplater-0.0.2.dist-info/entry_points.txt
cfgtemplater-0.0.2.dist-info/top_level.txt
cfgtemplater-0.0.2.dist-info/RECORD
