Metadata-Version: 2.1
Name: cfgtemplater
Version: 0.0.2
Summary: A tool to generate templates based on Jinja and YAML
Home-page: UNKNOWN
Author: xv0x7c0
Author-email: 13061441+xv0x7c0@users.noreply.github.com
License: UNKNOWN
Platform: UNKNOWN
Classifier: Programming Language :: Python :: 3
Requires-Dist: jinja2 (>=2.10)
Requires-Dist: ipaddress (>=1.0.22)
Requires-Dist: pyyaml (>=5.1)
